dispatk.py
setup.py
dispatk.egg-info/PKG-INFO
dispatk.egg-info/SOURCES.txt
dispatk.egg-info/dependency_links.txt
dispatk.egg-info/pbr.json
dispatk.egg-info/top_level.txt
dispatk.egg-info/zip-safe