Metadata-Version: 1.1
Name: dispatk
Version: 0.1
Summary: Multiple dispatcher on arguments values.
Home-page: https://github.com/hephs/dispatk
Author: hephaestus
Author-email: UNKNOWN
License: MIT
Keywords: multiple dispatch generic functions genericfunctions decorator
Platform: any
Classifier: Intended Audience :: Developers
Classifier: License :: OSI Approved :: MIT License
Classifier: Natural Language :: English
Classifier: Operating System :: OS Independent
Classifier: Programming Language :: Python
Classifier: Programming Language :: Python :: 2
Classifier: Programming Language :: Python :: 3
Classifier: Topic :: Software Development :: Libraries
Classifier: Topic :: Software Development :: Libraries :: Python Modules
